project_sunrise-0.1.0.dist-info/licenses/LICENSE
sunrise/__init__.py
sunrise/plot_MO.py
sunrise/version.py
sunrise/ADAPT/__init__.py
sunrise/ADAPT/adapt.py
sunrise/expval/__init__.py
sunrise/expval/fermionic_utils.py
sunrise/expval/fqe_expval.py
sunrise/expval/fqe_utils.py
sunrise/expval/minimize.py
sunrise/expval/optimize.py
sunrise/expval/pyscf_molecule.py
sunrise/expval/tcc_expval.py
sunrise/expval/tequila_expval.py
sunrise/expval/tcc_engine/__init__.py
sunrise/expval/tcc_engine/braket.py
sunrise/expval/tcc_engine/engine_braket.py
sunrise/expval/tcc_engine/evolve_civector.py
sunrise/expval/tcc_engine/evolve_pyscf.py
sunrise/fermionic_operations/__init__.py
sunrise/fermionic_operations/circuit.py
sunrise/fermionic_operations/fgateimpl.py
sunrise/fermionic_operations/gates.py
sunrise/fermionic_operations/givens_rotations.py
sunrise/fermionic_operations/orb_rotation_qubit.py
sunrise/graphical/__init__.py
sunrise/graphical/qpic_visualization.py
sunrise/graphical/core/__init__.py
sunrise/graphical/core/color.py
sunrise/graphical/core/gate.py
sunrise/graphical/core/shape.py
sunrise/graphical/core/state.py
sunrise/graphical/generic/__init__.py
sunrise/graphical/generic/circuit.py
sunrise/graphical/generic/gate.py
sunrise/graphical/generic/named.py
sunrise/graphical/quantum_chemistry/__init__.py
sunrise/graphical/quantum_chemistry/double_excitation.py
sunrise/graphical/quantum_chemistry/generic_exitation.py
sunrise/graphical/quantum_chemistry/orbital_rotator.py
sunrise/graphical/quantum_chemistry/pair_correlator.py
sunrise/graphical/quantum_chemistry/single_excitation.py
sunrise/hybridization/__init__.py
sunrise/hybridization/atom.py
sunrise/hybridization/hybridization.py
sunrise/hybridization/utils.py
sunrise/measurement/__init__.py
sunrise/measurement/hcb_measurement/__init__.py
sunrise/measurement/hcb_measurement/measurement_utils.py
sunrise/miscellaneous/__init__.py
sunrise/miscellaneous/bar.py
sunrise/miscellaneous/giuseppe.py
sunrise/molecules/__init__.py
sunrise/molecules/fermionic_base/__init__.py
project_sunrise-0.1.0.dist-info/METADATA
project_sunrise-0.1.0.dist-info/WHEEL
project_sunrise-0.1.0.dist-info/top_level.txt
project_sunrise-0.1.0.dist-info/RECORD
